{
  "tournament": {
    "name": "Wimbledon 2026",
    "location": "Londres, Gran Bretaña",
    "category": "Grand Slam",
    "surface": "Césped",
    "draw": "Individual Masculino (ATP)",
    "start": "2026-06-29",
    "final": "2026-07-12",
    "currentRound": "Final"
  },
  "bookmakers": ["OddsPeak", "GrassLine", "MatchPoint Bet"],
  "matches": [
    {
      "id": "R1-01",
      "date": "2026-07-01",
      "time": "6:00 a.m.",
      "court": "Court 2",
      "round": "Ronda 1",
      "status": "upcoming",
      "player1": { "name": "H. Hurkacz", "country": "Polonia", "flag": "🇵🇱", "rank": 9 },
      "player2": { "name": "S. Ofner", "country": "Austria", "flag": "🇦🇹", "rank": 41 },
      "odds": {
        "OddsPeak":     { "p1": 1.33, "p2": 3.30 },
        "GrassLine":    { "p1": 1.30, "p2": 3.50 },
        "MatchPoint Bet": { "p1": 1.28, "p2": 3.60 }
      },
      "ourProjection": { "p1": 78, "p2": 22 },
      "context": {
        "h2h": { "played": 1, "p1Wins": 1, "p2Wins": 0, "lastResult": "6-3 6-4 Hurkacz (Halle 2024)" },
        "form": { "p1": ["W", "W", "L"], "p2": ["W", "L", "W"] },
        "surfaceRecord": { "p1": "12-4 en césped (2025-26)", "p2": "6-6 en césped (2025-26)" },
        "keyStats": {
          "p1": { "acesPerMatch": 14.2, "firstServePct": 68, "breakPointsWonPct": 41 },
          "p2": { "acesPerMatch": 7.8, "firstServePct": 61, "breakPointsWonPct": 33 }
        },
        "notes": "Hurkacz llega como uno de los sacadores más sólidos del césped; Ofner viene de perder en primera ronda en Halle."
      }
    },
    {
      "id": "R1-02",
      "date": "2026-07-01",
      "time": "6:00 a.m.",
      "court": "Court 5",
      "round": "Ronda 1",
      "status": "upcoming",
      "player1": { "name": "J. Brooksby", "country": "Estados Unidos", "flag": "🇺🇸", "rank": 87 },
      "player2": { "name": "I. Buse", "country": "Perú", "flag": "🇵🇪", "rank": 126 },
      "odds": {
        "OddsPeak":     { "p1": 1.65, "p2": 2.20 },
        "GrassLine":    { "p1": 1.62, "p2": 2.25 },
        "MatchPoint Bet": { "p1": 1.60, "p2": 2.30 }
      },
      "ourProjection": { "p1": 57, "p2": 43 },
      "context": {
        "h2h": { "played": 0, "p1Wins": 0, "p2Wins": 0, "lastResult": "Sin precedentes" },
        "form": { "p1": ["W", "D", "W"], "p2": ["W", "W", "W"] },
        "surfaceRecord": { "p1": "8-5 en césped (carrera)", "p2": "3-2 en césped (carrera)" },
        "keyStats": {
          "p1": { "acesPerMatch": 6.1, "firstServePct": 63, "breakPointsWonPct": 39 },
          "p2": { "acesPerMatch": 5.4, "firstServePct": 60, "breakPointsWonPct": 36 }
        },
        "notes": "Buse llega en gran racha de challengers sobre hierba; Brooksby regresa de lesión con ritmo irregular."
      }
    },
    {
      "id": "R1-03",
      "date": "2026-07-01",
      "time": "6:00 a.m.",
      "court": "Court 8",
      "round": "Ronda 1",
      "status": "upcoming",
      "player1": { "name": "M. Fucsovics", "country": "Hungría", "flag": "🇭🇺", "rank": 64 },
      "player2": { "name": "L. Tien", "country": "Estados Unidos", "flag": "🇺🇸", "rank": 52 },
      "odds": {
        "OddsPeak":     { "p1": 2.10, "p2": 1.75 },
        "GrassLine":    { "p1": 2.05, "p2": 1.78 },
        "MatchPoint Bet": { "p1": 2.15, "p2": 1.72 }
      },
      "ourProjection": { "p1": 44, "p2": 56 },
      "context": {
        "h2h": { "played": 1, "p1Wins": 0, "p2Wins": 1, "lastResult": "7-6 6-4 Tien (Estoril 2025)" },
        "form": { "p1": ["L", "W", "W"], "p2": ["W", "W", "D"] },
        "surfaceRecord": { "p1": "5-6 en césped (2025-26)", "p2": "4-2 en césped (2025-26)" },
        "keyStats": {
          "p1": { "acesPerMatch": 8.9, "firstServePct": 64, "breakPointsWonPct": 37 },
          "p2": { "acesPerMatch": 7.2, "firstServePct": 66, "breakPointsWonPct": 42 }
        },
        "notes": "Tien llega en su mejor forma del año; partido parejo con leve favoritismo de mercado hacia él."
      }
    },
    {
      "id": "R1-04",
      "date": "2026-07-01",
      "time": "6:00 a.m.",
      "court": "Court 3",
      "round": "Ronda 1",
      "status": "upcoming",
      "player1": { "name": "S. Kwon", "country": "Corea del Sur", "flag": "🇰🇷", "rank": 81 },
      "player2": { "name": "T. Paul", "country": "Estados Unidos", "flag": "🇺🇸", "rank": 12 },
      "odds": {
        "OddsPeak":     { "p1": 3.75, "p2": 1.24 },
        "GrassLine":    { "p1": 3.60, "p2": 1.26 },
        "MatchPoint Bet": { "p1": 3.90, "p2": 1.22 }
      },
      "ourProjection": { "p1": 21, "p2": 79 },
      "context": {
        "h2h": { "played": 0, "p1Wins": 0, "p2Wins": 0, "lastResult": "Sin precedentes" },
        "form": { "p1": ["L", "W", "L"], "p2": ["W", "W", "W"] },
        "surfaceRecord": { "p1": "3-5 en césped (carrera)", "p2": "16-7 en césped (carrera)" },
        "keyStats": {
          "p1": { "acesPerMatch": 4.8, "firstServePct": 58, "breakPointsWonPct": 30 },
          "p2": { "acesPerMatch": 9.6, "firstServePct": 65, "breakPointsWonPct": 44 }
        },
        "notes": "Paul es uno de los favoritos ocultos del cuadro tras semifinales en Queen's; sin valor aparente en su lado."
      }
    },
    {
      "id": "R1-05",
      "date": "2026-07-01",
      "time": "7:10 a.m.",
      "court": "Court 14",
      "round": "Ronda 1",
      "status": "upcoming",
      "player1": { "name": "N. Mejia", "country": "Colombia", "flag": "🇨🇴", "rank": 158 },
      "player2": { "name": "M. Zheng", "country": "China", "flag": "🇨🇳", "rank": 71 },
      "odds": {
        "OddsPeak":     { "p1": 2.60, "p2": 1.52 },
        "GrassLine":    { "p1": 2.70, "p2": 1.50 },
        "MatchPoint Bet": { "p1": 2.55, "p2": 1.54 }
      },
      "ourProjection": { "p1": 34, "p2": 66 },
      "context": {
        "h2h": { "played": 0, "p1Wins": 0, "p2Wins": 0, "lastResult": "Sin precedentes" },
        "form": { "p1": ["W", "L", "W"], "p2": ["W", "D", "W"] },
        "surfaceRecord": { "p1": "1-3 en césped (carrera)", "p2": "9-4 en césped (2025-26)" },
        "keyStats": {
          "p1": { "acesPerMatch": 3.9, "firstServePct": 57, "breakPointsWonPct": 31 },
          "p2": { "acesPerMatch": 6.7, "firstServePct": 63, "breakPointsWonPct": 40 }
        },
        "notes": "Mejia debuta en el cuadro principal de Wimbledon; su juego de fondo de pista rinde menos en hierba rápida."
      }
    },
    {
      "id": "R1-06",
      "date": "2026-07-01",
      "time": "7:10 a.m.",
      "court": "Court 6",
      "round": "Ronda 1",
      "status": "upcoming",
      "player1": { "name": "R. Safiullin", "country": "Rusia", "flag": "🇷🇺", "rank": 55 },
      "player2": { "name": "B. Van de Zandschulp", "country": "Países Bajos", "flag": "🇳🇱", "rank": 68 },
      "odds": {
        "OddsPeak":     { "p1": 2.05, "p2": 1.78 },
        "GrassLine":    { "p1": 2.00, "p2": 1.80 },
        "MatchPoint Bet": { "p1": 2.10, "p2": 1.75 }
      },
      "ourProjection": { "p1": 42, "p2": 58 },
      "context": {
        "h2h": { "played": 2, "p1Wins": 1, "p2Wins": 1, "lastResult": "6-4 6-4 Van de Zandschulp (Rotterdam 2024)" },
        "form": { "p1": ["W", "W", "L"], "p2": ["D", "W", "W"] },
        "surfaceRecord": { "p1": "4-4 en césped (carrera)", "p2": "9-5 en césped (carrera, incl. QF Wimbledon 2021)" },
        "keyStats": {
          "p1": { "acesPerMatch": 7.0, "firstServePct": 62, "breakPointsWonPct": 35 },
          "p2": { "acesPerMatch": 8.4, "firstServePct": 64, "breakPointsWonPct": 38 }
        },
        "notes": "Van de Zandschulp tiene pedigrí en césped (llegó a cuartos en 2021); mercado lo respeta como leve favorito."
      }
    },
    {
      "id": "R1-07",
      "date": "2026-07-01",
      "time": "7:40 a.m.",
      "court": "Court 4",
      "round": "Ronda 1",
      "status": "upcoming",
      "player1": { "name": "A. Davidovich Fokina", "country": "España", "flag": "🇪🇸", "rank": 28 },
      "player2": { "name": "F. Marozsan", "country": "Hungría", "flag": "🇭🇺", "rank": 45 },
      "odds": {
        "OddsPeak":     { "p1": 1.70, "p2": 2.15 },
        "GrassLine":    { "p1": 1.68, "p2": 2.18 },
        "MatchPoint Bet": { "p1": 1.72, "p2": 2.12 }
      },
      "ourProjection": { "p1": 55, "p2": 45 },
      "context": {
        "h2h": { "played": 1, "p1Wins": 1, "p2Wins": 0, "lastResult": "6-2 6-3 Davidovich Fokina (Barcelona 2025)" },
        "form": { "p1": ["W", "L", "W"], "p2": ["W", "W", "L"] },
        "surfaceRecord": { "p1": "5-5 en césped (carrera)", "p2": "3-3 en césped (carrera)" },
        "keyStats": {
          "p1": { "acesPerMatch": 6.3, "firstServePct": 60, "breakPointsWonPct": 38 },
          "p2": { "acesPerMatch": 5.9, "firstServePct": 61, "breakPointsWonPct": 37 }
        },
        "notes": "Ninguno destaca en hierba históricamente; el mercado y nuestra proyección coinciden en un ligero favoritismo español."
      }
    },
    {
      "id": "R1-08",
      "date": "2026-07-01",
      "time": "7:40 a.m.",
      "court": "Court 1",
      "round": "Ronda 1",
      "status": "upcoming",
      "player1": { "name": "F. Tiafoe", "country": "Estados Unidos", "flag": "🇺🇸", "rank": 17 },
      "player2": { "name": "T. Atmane", "country": "Francia", "flag": "🇫🇷", "rank": 33 },
      "odds": {
        "OddsPeak":     { "p1": 1.75, "p2": 2.05 },
        "GrassLine":    { "p1": 1.70, "p2": 2.10 },
        "MatchPoint Bet": { "p1": 1.73, "p2": 2.08 }
      },
      "ourProjection": { "p1": 48, "p2": 52 },
      "context": {
        "h2h": { "played": 1, "p1Wins": 0, "p2Wins": 1, "lastResult": "7-6 6-7 7-6 Atmane (Cincinnati 2025)" },
        "form": { "p1": ["W", "D", "L"], "p2": ["W", "W", "W"] },
        "surfaceRecord": { "p1": "18-9 en césped (carrera)", "p2": "4-1 en césped (carrera)" },
        "keyStats": {
          "p1": { "acesPerMatch": 8.1, "firstServePct": 61, "breakPointsWonPct": 39 },
          "p2": { "acesPerMatch": 11.4, "firstServePct": 67, "breakPointsWonPct": 41 }
        },
        "notes": "Atmane llega en el mejor momento de su carrera; nuestra proyección le da una ligera ventaja pese a que el mercado favorece a Tiafoe por experiencia en Grand Slams.",
        "valueFlag": true
      }
    },
    {
      "id": "R1-09",
      "date": "2026-07-01",
      "time": "7:50 a.m.",
      "court": "Court 12",
      "round": "Ronda 1",
      "status": "upcoming",
      "player1": { "name": "D. Merida", "country": "España", "flag": "🇪🇸", "rank": 173 },
      "player2": { "name": "D. Medvedev", "country": "Rusia", "flag": "🇷🇺", "rank": 6 },
      "odds": {
        "OddsPeak":     { "p1": 6.50, "p2": 1.10 },
        "GrassLine":    { "p1": 6.00, "p2": 1.11 },
        "MatchPoint Bet": { "p1": 7.00, "p2": 1.08 }
      },
      "ourProjection": { "p1": 12, "p2": 88 },
      "context": {
        "h2h": { "played": 0, "p1Wins": 0, "p2Wins": 0, "lastResult": "Sin precedentes" },
        "form": { "p1": ["W", "W", "L"], "p2": ["W", "W", "D"] },
        "surfaceRecord": { "p1": "0-1 en césped (carrera)", "p2": "24-11 en césped (carrera, incl. final Wimbledon 2021)" },
        "keyStats": {
          "p1": { "acesPerMatch": 3.2, "firstServePct": 55, "breakPointsWonPct": 27 },
          "p2": { "acesPerMatch": 9.8, "firstServePct": 64, "breakPointsWonPct": 43 }
        },
        "notes": "Merida (clasificado, debut en el main draw) enfrenta a un excampeón subcampeón de Wimbledon; sin valor en ningún lado del mercado."
      }
    },
    {
      "id": "R2-01",
      "date": "2026-07-02",
      "time": "6:00 a.m.",
      "court": "Court 3",
      "round": "Ronda 2",
      "status": "upcoming",
      "player1": { "name": "A. de Minaur", "country": "Australia", "flag": "🇦🇺", "rank": 9 },
      "player2": { "name": "A. Mannarino", "country": "Francia", "flag": "🇫🇷", "rank": 44 },
      "odds": {
        "OddsPeak":     { "p1": 1.22, "p2": 3.90 },
        "GrassLine":    { "p1": 1.20, "p2": 4.10 },
        "MatchPoint Bet": { "p1": 1.24, "p2": 3.75 }
      },
      "ourProjection": { "p1": 81, "p2": 19 },
      "context": {
        "h2h": { "played": 6, "p1Wins": 5, "p2Wins": 1, "lastResult": "6-4 6-0 De Minaur (Libema Open, semifinal, 13 jun 2026)" },
        "surfaceRecord": { "p1": "En césped lidera el historial 2-1 sobre Mannarino", "p2": "Especialista de césped, pero perdió los 2 últimos ante De Minaur" },
        "notes": "De Minaur llega con un triunfo contundente muy reciente sobre este mismo rival en césped. El hándicap De Minaur -6.5 juegos paga +117 en Kalshi — valor interesante pese a ser favorito claro en el ganador."
      }
    },
    {
      "id": "R2-02",
      "date": "2026-07-02",
      "time": "6:00 a.m.",
      "court": "Court 5",
      "round": "Ronda 2",
      "status": "upcoming",
      "player1": { "name": "A. Fery", "country": "Gran Bretaña", "flag": "🇬🇧", "rank": 180 },
      "player2": { "name": "O. Virtanen", "country": "Finlandia", "flag": "🇫🇮", "rank": 85 },
      "odds": {
        "OddsPeak":     { "p1": 2.15, "p2": 1.68 },
        "GrassLine":    { "p1": 2.20, "p2": 1.65 },
        "MatchPoint Bet": { "p1": 2.10, "p2": 1.72 }
      },
      "ourProjection": { "p1": 42, "p2": 58 },
      "context": {
        "h2h": { "played": 0, "p1Wins": 0, "p2Wins": 0, "lastResult": "Sin precedentes" },
        "form": { "p1": ["W"], "p2": ["W"] },
        "notes": "Fery (wildcard local) venció a Dzumhur en R1; Virtanen firmó el resultado del torneo al eliminar al 4º cabeza de serie Ben Shelton en 5 sets — llega con moral altísima y es el ligero favorito del mercado."
      }
    },
    {
      "id": "R2-03",
      "date": "2026-07-02",
      "time": "6:00 a.m.",
      "court": "Court 8",
      "round": "Ronda 2",
      "status": "upcoming",
      "player1": { "name": "G. Diallo", "country": "Canadá", "flag": "🇨🇦", "rank": 38 },
      "player2": { "name": "L. Sonego", "country": "Italia", "flag": "🇮🇹", "rank": 52 },
      "odds": {
        "OddsPeak":     { "p1": 1.80, "p2": 2.05 },
        "GrassLine":    { "p1": 1.83, "p2": 2.00 },
        "MatchPoint Bet": { "p1": 1.78, "p2": 2.10 }
      },
      "ourProjection": { "p1": 62, "p2": 38 },
      "context": {
        "h2h": { "played": 1, "p1Wins": 0, "p2Wins": 1, "lastResult": "7-6(5) 2-6 7-6(7) Sonego (Auckland 2025) — pese a perder, Diallo ganó más puntos totales (114-110)" },
        "notes": "Diallo es considerado el mejor jugador de césped de los dos y llega en mejor forma actual. Cuota (1.81 ≈ 55.2% implícito) por debajo de nuestra estimación (62%) — la mejor pata de valor del día."
      }
    },
    {
      "id": "R2-04",
      "date": "2026-07-02",
      "time": "6:00 a.m.",
      "court": "Court 1",
      "round": "Ronda 2",
      "status": "upcoming",
      "player1": { "name": "T. Fritz", "country": "Estados Unidos", "flag": "🇺🇸", "rank": 6 },
      "player2": { "name": "P. Kypson", "country": "Estados Unidos", "flag": "🇺🇸", "rank": 113 },
      "odds": {
        "OddsPeak":     { "p1": 1.06, "p2": 9.50 },
        "GrassLine":    { "p1": 1.05, "p2": 10.50 },
        "MatchPoint Bet": { "p1": 1.07, "p2": 9.00 }
      },
      "ourProjection": { "p1": 95, "p2": 5 },
      "context": {
        "h2h": { "played": 0, "p1Wins": 0, "p2Wins": 0, "lastResult": "Sin precedentes" },
        "notes": "Brecha de experiencia en césped enorme: 61 victorias en la superficie para Fritz por solo 3 de Kypson. Fritz sacó 14 aces y 0 dobles faltas en R1 — favorito casi absoluto del día, sin valor en la cuota pero pata muy segura."
      }
    },
    {
      "id": "R2-05",
      "date": "2026-07-02",
      "time": "7:10 a.m.",
      "court": "Court 14",
      "round": "Ronda 2",
      "status": "upcoming",
      "player1": { "name": "Z. Svajda", "country": "Estados Unidos", "flag": "🇺🇸", "rank": 108 },
      "player2": { "name": "K. Majchrzak", "country": "Polonia", "flag": "🇵🇱", "rank": 89 },
      "odds": {
        "OddsPeak":     { "p1": 2.45, "p2": 1.65 },
        "GrassLine":    { "p1": 2.55, "p2": 1.62 },
        "MatchPoint Bet": { "p1": 2.35, "p2": 1.68 }
      },
      "ourProjection": { "p1": 39, "p2": 61 },
      "context": {
        "h2h": { "played": 2, "p1Wins": 1, "p2Wins": 1, "lastResult": "6-4 7-6(3) Svajda (Challenger Birmingham 2025) — pero Majchrzak lidera 1-0 en césped" },
        "notes": "Majchrzak viene de vencer a un rival de nivel (Tabilo) en sets corridos; ligero favorito de mercado y del modelo (61%)."
      }
    },
    {
      "id": "R2-06",
      "date": "2026-07-02",
      "time": "7:10 a.m.",
      "court": "Court 6",
      "round": "Ronda 2",
      "status": "upcoming",
      "player1": { "name": "Z. Bergs", "country": "Bélgica", "flag": "🇧🇪", "rank": 48 },
      "player2": { "name": "J. Faria", "country": "Portugal", "flag": "🇵🇹", "rank": 92 },
      "odds": {
        "OddsPeak":     { "p1": 1.33, "p2": 3.30 },
        "GrassLine":    { "p1": 1.30, "p2": 3.50 },
        "MatchPoint Bet": { "p1": 1.36, "p2": 3.15 }
      },
      "ourProjection": { "p1": 68, "p2": 32 },
      "context": {
        "h2h": { "played": 0, "p1Wins": 0, "p2Wins": 0, "lastResult": "Sin precedentes" },
        "notes": "El mercado (1.33 ≈ 75.2% implícito) es bastante más optimista con Bergs que el modelo (63%) — bajamos nuestra proyección a 68%. Dato curioso: varios analistas recomiendan a Faria como valor para ganar el Set 1."
      }
    },
    {
      "id": "R2-07",
      "date": "2026-07-02",
      "time": "Suspendido (continúa del 1 jul)",
      "court": "Court 12",
      "round": "Ronda 2",
      "status": "suspendido",
      "player1": { "name": "B. Nakashima", "country": "Estados Unidos", "flag": "🇺🇸", "rank": 31 },
      "player2": { "name": "J. L. Struff", "country": "Alemania", "flag": "🇩🇪", "rank": 74 },
      "odds": {
        "OddsPeak":     { "p1": 1.38, "p2": 3.04 },
        "GrassLine":    { "p1": 1.35, "p2": 3.20 },
        "MatchPoint Bet": { "p1": 1.42, "p2": 2.90 }
      },
      "ourProjection": { "p1": 66, "p2": 34 },
      "context": {
        "h2h": { "played": 0, "p1Wins": 0, "p2Wins": 0, "lastResult": "Sin precedentes" },
        "notes": "⚠️ Partido suspendido por lluvia y llevado al 2 de julio — al momento de este análisis va 2 sets a 2, así que las cuotas y proyección mostradas son las previas al partido y ya no reflejan la situación real. Nakashima llegaba con gran racha en césped (4-1 en 2026, semifinal en Queen's) pero el marcador parejo muestra que Struff está compitiendo de igual a igual."
      }
    },
    {
      "id": "R2-08",
      "date": "2026-07-02",
      "time": "7:30 a.m.",
      "court": "Court 4",
      "round": "Ronda 2",
      "status": "upcoming",
      "player1": { "name": "J. Fearnley", "country": "Gran Bretaña", "flag": "🇬🇧", "rank": 85 },
      "player2": { "name": "J. Munar", "country": "España", "flag": "🇪🇸", "rank": 63 },
      "odds": {
        "OddsPeak":     { "p1": 2.20, "p2": 1.66 },
        "GrassLine":    { "p1": 2.30, "p2": 1.63 },
        "MatchPoint Bet": { "p1": 2.10, "p2": 1.70 }
      },
      "ourProjection": { "p1": 42, "p2": 58 },
      "context": {
        "h2h": { "played": 0, "p1Wins": 0, "p2Wins": 0, "lastResult": "Sin precedentes" },
        "notes": "Munar es favorito de los modelos (54-61%), pero varios analistas destacan a Fearnley como pick de valor a +130: remontó de 2 sets abajo en R1, tiene al público de Wimbledon a favor y Munar arrastra un pobre récord en césped (8-18, dominance ratio 0.93). Pick especulativo de valor, no apto para una combinada segura."
      }
    },
    {
      "id": "R2-09",
      "date": "2026-07-02",
      "time": "Suspendido (continúa del 1 jul)",
      "court": "Court 2",
      "round": "Ronda 2",
      "status": "suspendido",
      "player1": { "name": "R. Jódar", "country": "España", "flag": "🇪🇸", "rank": 26 },
      "player2": { "name": "P. Carreño Busta", "country": "España", "flag": "🇪🇸", "rank": 71 },
      "odds": {
        "OddsPeak":     { "p1": 1.30, "p2": 3.50 },
        "GrassLine":    { "p1": 1.28, "p2": 3.75 },
        "MatchPoint Bet": { "p1": 1.32, "p2": 3.30 }
      },
      "ourProjection": { "p1": 74, "p2": 26 },
      "context": {
        "h2h": { "played": 1, "p1Wins": 1, "p2Wins": 0, "lastResult": "Jódar remontó 2 sets abajo para ganar 4-6 4-6 6-1 6-2 6-2 (Roland Garros 2026, R4)" },
        "notes": "⚠️ Partido suspendido y continúa el 2 de julio — actualmente Carreño Busta (34 años) va arriba 2 sets a 1 sobre el joven favorito Jódar (19 años). Las cuotas mostradas son las previas al partido; la sorpresa en marcha le da valor a Carreño Busta si algún libro sigue ofreciendo el partido en vivo."
      }
    },
    {
      "id": "R2-10",
      "date": "2026-07-02",
      "time": "7:40 a.m.",
      "court": "Court 7",
      "round": "Ronda 2",
      "status": "upcoming",
      "player1": { "name": "K. Khachanov", "country": "Rusia", "flag": "🇷🇺", "rank": 20 },
      "player2": { "name": "Y. Hanfmann", "country": "Alemania", "flag": "🇩🇪", "rank": 96 },
      "odds": {
        "OddsPeak":     { "p1": 1.63, "p2": 2.25 },
        "GrassLine":    { "p1": 1.60, "p2": 2.35 },
        "MatchPoint Bet": { "p1": 1.66, "p2": 2.15 }
      },
      "ourProjection": { "p1": 64, "p2": 36 },
      "context": {
        "h2h": { "played": 1, "p1Wins": 1, "p2Wins": 0, "lastResult": "Khachanov ganó el único precedente" },
        "notes": "Modelos entre 63-65% para Khachanov, apenas por encima de la cuota (1.63 ≈ 61.5% implícito) — leve valor. El pick recomendado por Dimers es Khachanov a ganar el Set 1."
      }
    },
    {
      "id": "R2-11",
      "date": "2026-07-02",
      "time": "8:20 a.m.",
      "court": "Court 9",
      "round": "Ronda 2",
      "status": "upcoming",
      "player1": { "name": "Q. Halys", "country": "Francia", "flag": "🇫🇷", "rank": 58 },
      "player2": { "name": "M. Giron", "country": "Estados Unidos", "flag": "🇺🇸", "rank": 64 },
      "odds": {
        "OddsPeak":     { "p1": 1.98, "p2": 1.94 },
        "GrassLine":    { "p1": 1.95, "p2": 1.97 },
        "MatchPoint Bet": { "p1": 2.00, "p2": 1.90 }
      },
      "ourProjection": { "p1": 48, "p2": 52 },
      "context": {
        "h2h": { "played": 1, "p1Wins": 0, "p2Wins": 1, "lastResult": "Giron ganó 7-5 3-6 6-7(5) 7-5 8-6 (Paris 2020) — nunca jugaron en césped" },
        "notes": "El partido más parejo del día — prácticamente un lanzamiento de moneda. Giron convierte más puntos de quiebre (32% vs 23%). Sin valor claro para ninguno de los dos lados; lo dejamos fuera de la combinada recomendada por la incertidumbre."
      }
    },
    {
      "id": "R2-12",
      "date": "2026-07-02",
      "time": "9:10 a.m.",
      "court": "Court 1",
      "round": "Ronda 2",
      "status": "upcoming",
      "player1": { "name": "V. Royer", "country": "Francia", "flag": "🇫🇷", "rank": 75 },
      "player2": { "name": "A. Zverev", "country": "Alemania", "flag": "🇩🇪", "rank": 3 },
      "odds": {
        "OddsPeak":     { "p1": 12.00, "p2": 1.05 },
        "GrassLine":    { "p1": 13.00, "p2": 1.04 },
        "MatchPoint Bet": { "p1": 11.00, "p2": 1.06 }
      },
      "ourProjection": { "p1": 10, "p2": 90 },
      "context": {
        "h2h": { "played": 1, "p1Wins": 0, "p2Wins": 1, "lastResult": "Zverev ganó en sets corridos (Masters de Shanghai)" },
        "notes": "Zverev acaba de ganar Roland Garros y busca su 2º Grand Slam seguido, pero cayó en R1 de Wimbledon 2025 — el césped sigue siendo su superficie más floja. El verdadero valor está en el hándicap Zverev -7.5 juegos (+108 ≈ 48% implícito vs 72% del modelo) — uno de los mayores edges que encontramos en todo el análisis."
      }
    },
    {
      "id": "R2-13",
      "date": "2026-07-02",
      "time": "9:30 a.m.",
      "court": "Court 2",
      "round": "Ronda 2",
      "status": "upcoming",
      "player1": { "name": "F. Tiafoe", "country": "Estados Unidos", "flag": "🇺🇸", "rank": 17 },
      "player2": { "name": "J. Choinski", "country": "Gran Bretaña", "flag": "🇬🇧", "rank": 100 },
      "odds": {
        "OddsPeak":     { "p1": 1.15, "p2": 5.50 },
        "GrassLine":    { "p1": 1.13, "p2": 6.00 },
        "MatchPoint Bet": { "p1": 1.17, "p2": 5.00 }
      },
      "ourProjection": { "p1": 78, "p2": 22 },
      "context": {
        "h2h": { "played": 0, "p1Wins": 0, "p2Wins": 0, "lastResult": "Sin precedentes" },
        "notes": "Tiafoe llega con título en Halle y 6 victorias seguidas en césped, pero en su propio R1 sacó mal (58% de primeros, 6 dobles faltas) mientras Choinski sacó casi perfecto (18 aces, 1 doble falta) con el público de casa a favor. Riesgo real que la cuota (≈87.7% implícito) no refleja del todo."
      }
    },
    {
      "id": "R2-14",
      "date": "2026-07-02",
      "time": "4:30 p.m.",
      "court": "Court 10",
      "round": "Ronda 2",
      "status": "upcoming",
      "player1": { "name": "J. Duckworth", "country": "Australia", "flag": "🇦🇺", "rank": 93 },
      "player2": { "name": "F. Cobolli", "country": "Italia", "flag": "🇮🇹", "rank": 32 },
      "odds": {
        "OddsPeak":     { "p1": 2.95, "p2": 1.50 },
        "GrassLine":    { "p1": 3.15, "p2": 1.47 },
        "MatchPoint Bet": { "p1": 2.80, "p2": 1.53 }
      },
      "ourProjection": { "p1": 32, "p2": 68 },
      "context": {
        "h2h": { "played": 2, "p1Wins": 1, "p2Wins": 1, "lastResult": "1-1 en enfrentamientos previos, nunca en césped" },
        "notes": "Cobolli tiene mejor forma en el último año (60% vs 57.3%) y el césped es la superficie más floja de Duckworth (52% de victorias). Cuota (1.50 ≈ 67.2% implícito) prácticamente en línea con nuestra proyección — pata justa, sin gran valor pero confiable."
      }
    },
    {
      "id": "R2-15",
      "date": "2026-07-02",
      "time": "9:30 a.m.",
      "court": "Court 3",
      "round": "Ronda 2",
      "status": "upcoming",
      "player1": { "name": "J. Lehečka", "country": "República Checa", "flag": "🇨🇿", "rank": 12 },
      "player2": { "name": "A. Molčan", "country": "Eslovaquia", "flag": "🇸🇰", "rank": 96 },
      "odds": {
        "OddsPeak":     { "p1": 1.28, "p2": 4.20 },
        "GrassLine":    { "p1": 1.25, "p2": 4.50 },
        "MatchPoint Bet": { "p1": 1.31, "p2": 3.90 }
      },
      "ourProjection": { "p1": 80, "p2": 20 },
      "context": {
        "h2h": { "played": 0, "p1Wins": 0, "p2Wins": 0, "lastResult": "Sin precedentes" },
        "notes": "Lehečka tiene el saque y el derechazo ideales para el césped, más de 80 puestos de ranking a favor, y llega descansado tras un R1 cómodo ante Popyrin. Molčan tuvo que remontar un 4-setter interrumpido por lluvia en dos días — desgaste físico real. Favorito muy sólido."
      }
    },
    {
      "id": "R2-16",
      "date": "2026-07-02",
      "time": "9:40 a.m.",
      "court": "Court 1",
      "round": "Ronda 2",
      "status": "upcoming",
      "player1": { "name": "M. Berrettini", "country": "Italia", "flag": "🇮🇹", "rank": 86 },
      "player2": { "name": "A. Fils", "country": "Francia", "flag": "🇫🇷", "rank": 15 },
      "odds": {
        "OddsPeak":     { "p1": 2.35, "p2": 1.58 },
        "GrassLine":    { "p1": 2.45, "p2": 1.55 },
        "MatchPoint Bet": { "p1": 2.25, "p2": 1.61 }
      },
      "ourProjection": { "p1": 42, "p2": 58 },
      "context": {
        "h2h": { "played": 0, "p1Wins": 0, "p2Wins": 0, "lastResult": "Sin precedentes" },
        "notes": "Fils es favorito de los modelos (56-61%), pero el propio consenso de apostadores señala a Berrettini como la mejor jugada de valor al precio actual (+135), pese a ser el menos probable de ganar. Pick especulativo, no apto para una combinada segura."
      }
    },
    {
      "id": "R2-17",
      "date": "2026-07-02",
      "time": "10:20 a.m.",
      "court": "Court 5",
      "round": "Ronda 2",
      "status": "upcoming",
      "player1": { "name": "K. Jacquet", "country": "Francia", "flag": "🇫🇷", "rank": 131 },
      "player2": { "name": "A. Bublik", "country": "Kazajistán", "flag": "🇰🇿", "rank": 25 },
      "odds": {
        "OddsPeak":     { "p1": 3.60, "p2": 1.30 },
        "GrassLine":    { "p1": 3.80, "p2": 1.27 },
        "MatchPoint Bet": { "p1": 3.40, "p2": 1.33 }
      },
      "ourProjection": { "p1": 26, "p2": 74 },
      "context": {
        "h2h": { "played": 0, "p1Wins": 0, "p2Wins": 0, "lastResult": "Sin precedentes" },
        "notes": "Bublik es favorito (75% del modelo) pero es un jugador de rendimiento muy irregular partido a partido — la pata de mayor incertidumbre entre los 'ganador simple' masculinos del día."
      }
    },
    {
      "id": "R2-18",
      "date": "2026-07-02",
      "time": "10:50 a.m.",
      "court": "Court 1",
      "round": "Ronda 2",
      "status": "upcoming",
      "player1": { "name": "J. Menšik", "country": "República Checa", "flag": "🇨🇿", "rank": 18 },
      "player2": { "name": "G. Dimitrov", "country": "Bulgaria", "flag": "🇧🇬", "rank": 146 },
      "odds": {
        "OddsPeak":     { "p1": 1.53, "p2": 2.45 },
        "GrassLine":    { "p1": 1.50, "p2": 2.55 },
        "MatchPoint Bet": { "p1": 1.56, "p2": 2.35 }
      },
      "ourProjection": { "p1": 62, "p2": 38 },
      "context": {
        "h2h": { "played": 0, "p1Wins": 0, "p2Wins": 0, "lastResult": "Sin precedentes" },
        "notes": "Menšik tiene mejor forma actual (65.5% implícito en la cuota), pero Dimitrov conserva una experiencia en césped muy superior — el pick de valor señalado por analistas es Dimitrov a ganar el Set 1, no el partido completo."
      }
    },
    {
      "id": "R3-01",
      "date": "2026-07-03",
      "time": "1:30 p.m.",
      "court": "Centre Court",
      "round": "Ronda 3",
      "status": "upcoming",
      "player1": { "name": "N. Djokovic", "country": "Serbia", "flag": "🇷🇸", "rank": 5 },
      "player2": { "name": "A. Rinderknech", "country": "Francia", "flag": "🇫🇷", "rank": 85 },
      "odds": {
        "OddsPeak":     { "p1": 1.12, "p2": 6.00 },
        "GrassLine":    { "p1": 1.10, "p2": 6.50 },
        "MatchPoint Bet": { "p1": 1.14, "p2": 5.50 }
      },
      "ourProjection": { "p1": 87, "p2": 13 },
      "context": {
        "h2h": { "played": 0, "p1Wins": 0, "p2Wins": 0, "lastResult": "Sin precedentes" },
        "notes": "Rinderknech tiene un juego de potencia que podría exigirle más de la cuenta a Djokovic (39 años), pero sigue siendo un favorito abrumador. No encontramos línea de hándicap de juegos publicada para este partido — la cuota de mercado (≈89-92% implícito) ya refleja bien la brecha."
      }
    },
    {
      "id": "R3-02",
      "date": "2026-07-03",
      "time": "1:00 p.m.",
      "court": "Centre Court",
      "round": "Ronda 3",
      "status": "upcoming",
      "player1": { "name": "A. Sabalenka", "country": "Bielorrusia", "flag": "🇧🇾", "rank": 1 },
      "player2": { "name": "J. Ostapenko", "country": "Letonia", "flag": "🇱🇻", "rank": 30 },
      "odds": {
        "OddsPeak":     { "p1": 1.22, "p2": 4.33 },
        "GrassLine":    { "p1": 1.19, "p2": 4.60 },
        "MatchPoint Bet": { "p1": 1.25, "p2": 4.10 }
      },
      "ourProjection": { "p1": 79, "p2": 21 },
      "context": {
        "h2h": { "played": 0, "p1Wins": 0, "p2Wins": 0, "lastResult": "Ostapenko venció a Sabalenka en sets corridos en Stuttgart 2025 (superficie distinta)" },
        "notes": "Sabalenka no es tan sólida en césped (perdió feo ante Pegula en Berlín, y necesitó remontar de 2-5 abajo ante Kessler en R2). Mercados de valor: Ostapenko +4.5 juegos de hándicap tiene valor según varias fuentes — Sabalenka no siempre gana con margen amplio. En total de juegos, el pick recomendado es Más de 21.5 (línea baja, casi cantada)."
      }
    },
    {
      "id": "R3-03",
      "date": "2026-07-03",
      "time": "6:30 p.m.",
      "court": "Centre Court",
      "round": "Ronda 3",
      "status": "upcoming",
      "player1": { "name": "F. Auger-Aliassime", "country": "Canadá", "flag": "🇨🇦", "rank": 9 },
      "player2": { "name": "M. Zheng", "country": "Estados Unidos", "flag": "🇺🇸", "rank": 178 },
      "odds": {
        "OddsPeak":     { "p1": 1.16, "p2": 5.50 },
        "GrassLine":    { "p1": 1.14, "p2": 6.00 },
        "MatchPoint Bet": { "p1": 1.18, "p2": 5.00 }
      },
      "ourProjection": { "p1": 84, "p2": 16 },
      "context": {
        "h2h": { "played": 0, "p1Wins": 0, "p2Wins": 0, "lastResult": "Sin precedentes" },
        "notes": "Auger-Aliassime enfrentó solo 2 break points en sus primeras dos rondas — saque casi perfecto. Zheng (qualifier) llega en racha de 5 victorias seguidas pero desgastado tras un partido a 4 sets. No encontramos línea de hándicap/juegos publicada para este cruce."
      }
    },
    {
      "id": "R3-04",
      "date": "2026-07-03",
      "time": "3:30 p.m.",
      "court": "Court 1",
      "round": "Ronda 3",
      "status": "upcoming",
      "player1": { "name": "J. Sinner", "country": "Italia", "flag": "🇮🇹", "rank": 1 },
      "player2": { "name": "J. Brooksby", "country": "Estados Unidos", "flag": "🇺🇸", "rank": 81 },
      "odds": {
        "OddsPeak":     { "p1": 1.03, "p2": 13.00 },
        "GrassLine":    { "p1": 1.02, "p2": 15.00 },
        "MatchPoint Bet": { "p1": 1.04, "p2": 12.00 }
      },
      "ourProjection": { "p1": 95, "p2": 5 },
      "context": {
        "h2h": { "played": 1, "p1Wins": 1, "p2Wins": 0, "lastResult": "Sinner ganó 7-6(2) 6-1 en pista dura (Washington 2021)" },
        "notes": "Mercado de valor real: hándicap Sinner -8.5 juegos a cuota ~2.10 (bet365). Es un margen exigente — según los analistas, Brooksby solo necesita ganar 12+ juegos en un partido a 3 sets (o forzar un 4º set) para que el hándicap falle, así que no es una apuesta tan cómoda como sugiere la superioridad de Sinner. Alternativa combinada: 'Sinner gana y Menos de 29.5 juegos' a cuota 2.00."
      }
    },
    {
      "id": "R3-05",
      "date": "2026-07-03",
      "time": "1:00 p.m.",
      "court": "Court 1",
      "round": "Ronda 3",
      "status": "upcoming",
      "player1": { "name": "N. Osaka", "country": "Japón", "flag": "🇯🇵", "rank": 14 },
      "player2": { "name": "D. Kasatkina", "country": "Australia", "flag": "🇦🇺", "rank": 20 },
      "odds": {
        "OddsPeak":     { "p1": 1.20, "p2": 4.50 },
        "GrassLine":    { "p1": 1.17, "p2": 4.90 },
        "MatchPoint Bet": { "p1": 1.23, "p2": 4.20 }
      },
      "ourProjection": { "p1": 78, "p2": 22 },
      "context": {
        "h2h": { "played": 3, "p1Wins": 3, "p2Wins": 0, "lastResult": "Osaka domina el historial 3-0, aunque nunca jugaron en césped" },
        "notes": "Osaka no perdió un set en el torneo; Kasatkina llegó a la distancia completa en sus dos partidos previos. Mercado de valor: bet365 ofrece un Bet Builder con Kasatkina +4.5 juegos + Más de 20.5 juegos + Más de 0.5 tiebreaks a cuota 4.50 — una combinación específica de props en un solo boleto."
      }
    },
    {
      "id": "R3-06",
      "date": "2026-07-03",
      "time": "10:50 a.m.",
      "court": "Court 1",
      "round": "Ronda 3",
      "status": "upcoming",
      "player1": { "name": "C. Gauff", "country": "Estados Unidos", "flag": "🇺🇸", "rank": 7 },
      "player2": { "name": "C. Liu", "country": "Estados Unidos", "flag": "🇺🇸", "rank": 80 },
      "odds": {
        "OddsPeak":     { "p1": 1.10, "p2": 7.00 },
        "GrassLine":    { "p1": 1.08, "p2": 7.50 },
        "MatchPoint Bet": { "p1": 1.12, "p2": 6.50 }
      },
      "ourProjection": { "p1": 85, "p2": 15 },
      "context": {
        "h2h": { "played": 1, "p1Wins": 1, "p2Wins": 0, "lastResult": "Gauff ganó 6-4 6-2 en el ASB Classic 2024" },
        "notes": "Duelo 100% estadounidense. Liu llegó a su primera 3ª ronda de Wimbledon en la carrera tras vencer en sets corridos. No encontramos línea de hándicap/juegos publicada — la cuota (≈90% implícito) ya es muy corta."
      }
    },
    {
      "id": "R3-07",
      "date": "2026-07-03",
      "time": "4:00 p.m.",
      "court": "Court 2",
      "round": "Ronda 3",
      "status": "upcoming",
      "player1": { "name": "T. Paul", "country": "Estados Unidos", "flag": "🇺🇸", "rank": 12 },
      "player2": { "name": "H. Hurkacz", "country": "Polonia", "flag": "🇵🇱", "rank": 44 },
      "odds": {
        "OddsPeak":     { "p1": 1.70, "p2": 2.15 },
        "GrassLine":    { "p1": 1.66, "p2": 2.25 },
        "MatchPoint Bet": { "p1": 1.74, "p2": 2.05 }
      },
      "ourProjection": { "p1": 61, "p2": 39 },
      "context": {
        "h2h": { "played": 4, "p1Wins": 3, "p2Wins": 1, "lastResult": "Paul lidera 3-1, pero nunca se enfrentaron en césped" },
        "notes": "Paul llega de la final de Queen's y con buen nivel en la gira de arcilla; el mercado (1.70 ≈ 58.8% implícito) queda algo por debajo del modelo (61%) — leve valor en Paul. No encontramos línea de hándicap/juegos publicada."
      }
    },
    {
      "id": "R3-08",
      "date": "2026-07-03",
      "time": "2:30 p.m.",
      "court": "Court 3",
      "round": "Ronda 3",
      "status": "upcoming",
      "player1": { "name": "D. Medvedev", "country": "Rusia", "flag": "🇷🇺", "rank": 8 },
      "player2": { "name": "J. L. Struff", "country": "Alemania", "flag": "🇩🇪", "rank": 55 },
      "odds": {
        "OddsPeak":     { "p1": 1.19, "p2": 4.70 },
        "GrassLine":    { "p1": 1.13, "p2": 5.50 },
        "MatchPoint Bet": { "p1": 1.22, "p2": 4.30 }
      },
      "ourProjection": { "p1": 80, "p2": 20 },
      "context": {
        "h2h": { "played": 3, "p1Wins": 2, "p2Wins": 1, "lastResult": "Medvedev lidera en sets 20-8, pero nunca le ganó a Struff en sets corridos sobre césped" },
        "notes": "Medvedev necesitó 4 sets para superar a Merida en R2 (arrancó lento). Mercados de valor: Más de 35.5 juegos totales es el pick recomendado, y 'Más de 3.5 sets' (el partido llega a un 4º set) paga cuota ~1.80 — respaldado por el dato concreto de que Medvedev nunca resolvió en sets corridos ante Struff en césped."
      }
    },
    {
      "id": "F-01",
      "date": "2026-07-11",
      "time": "9:00 a.m.",
      "court": "Centre Court",
      "round": "Final",
      "status": "upcoming",
      "player1": { "name": "K. Muchová", "country": "Rep. Checa", "flag": "🇨🇿", "rank": 11 },
      "player2": { "name": "L. Nosková", "country": "Rep. Checa", "flag": "🇨🇿", "rank": 13 },
      "odds": {
        "OddsPeak":     { "p1": 1.75, "p2": 2.10 },
        "GrassLine":    { "p1": 1.71, "p2": 2.18 },
        "MatchPoint Bet": { "p1": 1.79, "p2": 2.05 }
      },
      "ourProjection": { "p1": 55, "p2": 45 },
      "context": {
        "h2h": { "played": 1, "p1Wins": 1, "p2Wins": 0, "lastResult": "Muchová ganó a 3 sets 6-7 6-4 6-2 (US Open 2025)" },
        "form": { "p1": ["W", "W", "W"], "p2": ["W", "W", "W"] },
        "surfaceRecord": { "p1": "11-1 en césped en 2026", "p2": "11-1 en césped en 2026" },
        "notes": "Final 100% checa por primera vez en la historia de Wimbledon. Muchová (29 años) llega a su primera final de Grand Slam tras remontar y ganar un super-tiebreak 10-8 a Coco Gauff en semis; Nosková (21) busca ser la campeona más joven de Wimbledon desde Petra Kvitová en 2011, tras un cómodo 6-4 6-4 a Marta Kostyuk. Perfiles casi idénticos (ambas 11-1 en césped este año, ranking similar): partido genuinamente parejo, sin edge claro en el ganador. Mercado de valor real: Más de 23.5 juegos totales — varias fuentes lo destacan como la mejor jugada del día, dado que el único precedente entre ambas fue a 3 sets."
      }
    },
    {
      "id": "F-02",
      "date": "2026-07-12",
      "time": "9:00 a.m.",
      "court": "Centre Court",
      "round": "Final",
      "status": "upcoming",
      "player1": { "name": "J. Sinner", "country": "Italia", "flag": "🇮🇹", "rank": 1 },
      "player2": { "name": "A. Zverev", "country": "Alemania", "flag": "🇩🇪", "rank": 3 },
      "odds": {
        "OddsPeak":     { "p1": 1.22, "p2": 4.20 },
        "GrassLine":    { "p1": 1.19, "p2": 4.50 },
        "MatchPoint Bet": { "p1": 1.25, "p2": 4.00 }
      },
      "ourProjection": { "p1": 78, "p2": 22 },
      "context": {
        "h2h": { "played": 14, "p1Wins": 10, "p2Wins": 4, "lastResult": "Sinner ganó 9 partidos seguidos, incluída la final de Madrid 2026" },
        "form": { "p1": ["W", "W", "W"], "p2": ["W", "W", "W"] },
        "notes": "Sinner defiende el título tras vencer a Djokovic en semis (6-4 6-4 6-4); Zverev llegó a su primera final de Wimbledon superando a Fery en sets corridos, un camino más sencillo que el de Sinner. El historial es abrumador: Sinner domina 10-4 y viene de 9 triunfos consecutivos, incluyendo las 4 finales que jugaron en 2026 (Indian Wells, Miami, Monte Carlo y Madrid). El mercado (≈82% implícito) está en línea con nuestra proyección — sin valor real en el ganador, uno de los favoritos más sólidos de todo el torneo. Cuidado con el mercado de 'Más de 20 juegos': la línea es muy baja para una final a 5 sets y no encontramos con certeza si es el total correcto del partido completo — la marcamos como referencia, no como pick confirmado."
      }
    }
  ],
  "disclaimer": "Datos y cuotas simulados con fines ilustrativos y educativos. No constituye una recomendación de apuesta. Juega con responsabilidad.",
  "_generated": {
    "date": "2026-07-01",
    "timestamp": "2026-07-01T00:00:00.000Z"
  }
}
